musicbird/__init__.py
musicbird/__main__.py
musicbird/config.py
musicbird/copy.py
musicbird/data/default_config.yml
musicbird/db.py
musicbird/encode.py
musicbird/encoder.py
musicbird/file.py
musicbird/prune.py
musicbird/run.py
musicbird/scan.py
musicbird/scanner.py
musicbird-0.1.8.dist-info/entry_points.txt
musicbird-0.1.8.dist-info/LICENSE
musicbird-0.1.8.dist-info/WHEEL
musicbird-0.1.8.dist-info/METADATA
musicbird-0.1.8.dist-info/RECORD
