Metadata-Version: 2.1
Name: musicbird
Version: 0.1.8
Summary: Convert your music library on-the-fly!
Home-page: https://github.com/maxhoesel/musicbird
License: GPL-3.0-or-later
Keywords: musicbird,media,conversion,ffmpeg
Author: Max Hösel
Author-email: musicbird@maxhoesel.de
Requires-Python: >=3.6.2,<3.10
Classifier: Development Status :: 5 - Production/Stable
Classifier: License :: OSI Approved :: GNU General Public License v3 or later (GPLv3+)
Classifier: Programming Language :: Python :: 3
Classifier: Programming Language :: Python :: 3.7
Classifier: Programming Language :: Python :: 3.8
Classifier: Programming Language :: Python :: 3.9
Classifier: Topic :: Multimedia :: Sound/Audio :: Conversion
Provides-Extra: docs
Requires-Dist: PyYAML (>=6.0,<7.0)
Requires-Dist: Sphinx (>=4.3.2,<5.0.0); extra == "docs"
Requires-Dist: ffmpeg-python (>=0.2.0,<0.3.0)
Requires-Dist: importlib-metadata (>=1.0,<2.0); python_version < "3.8"
Requires-Dist: schema (>=0.7.5,<0.8.0)
Requires-Dist: sphinx-rtd-theme (>=1.0.0,<2.0.0); extra == "docs"
Requires-Dist: sphinxcontrib-napoleon (>=0.7,<0.8); extra == "docs"
Project-URL: Repository, https://github.com/maxhoesel/musicbird
